Metadata-Version: 2.1
Name: twine-unofficial
Version: 4.0.2.1
Summary: Collection of utilities for publishing packages on PyPI
Home-page: https://twine.readthedocs.io/
Author: Donald Stufft and individual contributors
Author-email: donald@stufft.io
Project-URL: Source, https://github.com/strayge/twine-unofficial/
Project-URL: Documentation, https://twine.readthedocs.io/en/latest/
Project-URL: Packaging tutorial, https://packaging.python.org/tutorials/packaging-projects/
Classifier: Intended Audience :: Developers
Classifier: License :: OSI Approved :: Apache Software License
Classifier: Natural Language :: English
Classifier: Operating System :: MacOS :: MacOS X
Classifier: Operating System :: POSIX
Classifier: Operating System :: POSIX :: BSD
Classifier: Operating System :: POSIX :: Linux
Classifier: Operating System :: Microsoft :: Windows
Classifier: Programming Language :: Python
Classifier: Programming Language :: Python :: 3
Classifier: Programming Language :: Python :: 3 :: Only
Classifier: Programming Language :: Python :: 3.7
Classifier: Programming Language :: Python :: 3.8
Classifier: Programming Language :: Python :: 3.9
Classifier: Programming Language :: Python :: 3.10
Classifier: Programming Language :: Python :: Implementation :: CPython
Requires-Python: >=3.7
License-File: LICENSE
Requires-Dist: pkginfo (<1.9.3,>=1.8.1)
Requires-Dist: readme-renderer (>=35.0)
Requires-Dist: requests (>=2.20)
Requires-Dist: requests-toolbelt (!=0.9.0,>=0.8.0)
Requires-Dist: urllib3 (>=1.26.0)
Requires-Dist: importlib-metadata (>=3.6)
Requires-Dist: keyring (>=15.1)
Requires-Dist: rfc3986 (>=1.4.0)
Requires-Dist: rich (>=12.0.0)
